ignition_kernel/__init__.py
ignition_kernel/__main__.py
ignition_kernel/provisioner.py
ignition_jupyter_kernel-0.7.3.dist-info/LICENSE
ignition_jupyter_kernel-0.7.3.dist-info/METADATA
ignition_jupyter_kernel-0.7.3.dist-info/WHEEL
ignition_jupyter_kernel-0.7.3.dist-info/entry_points.txt
ignition_jupyter_kernel-0.7.3.dist-info/top_level.txt
ignition_jupyter_kernel-0.7.3.dist-info/RECORD
