Metadata-Version: 2.1
Name: ignition-jupyter-kernel
Version: 0.7.3
Summary: Allow Jupyter to connect to a kernel running on a configured Ignition instance.
Author-email: Andrew Geiger <andrew@corsosystems.com>
Project-URL: Homepage, https://github.com/ignition-kernel/ignition-kernel
Project-URL: Source, https://github.com/ignition-kernel/ignition-kernel
Classifier: Development Status :: 4 - Beta
Classifier: Programming Language :: Python :: 3
Classifier: License :: OSI Approved :: Apache Software License
Classifier: Operating System :: OS Independent
Requires-Python: >=3.6.1
License-File: LICENSE
